seq_tools-1.0.10.dist-info/DESCRIPTION.rst
seq_tools-1.0.10.dist-info/METADATA
seq_tools-1.0.10.dist-info/RECORD
seq_tools-1.0.10.dist-info/WHEEL
seq_tools-1.0.10.dist-info/entry_points.txt
seq_tools-1.0.10.dist-info/metadata.json
seq_tools-1.0.10.dist-info/top_level.txt
seqtools/__init__.py
seqtools/align.py
seqtools/basics.py
seqtools/errors.py
seqtools/old_graph.py
seqtools/quantification.py
seqtools/stream.py
seqtools/cli/__init__.py
seqtools/cli/cli_front.py
seqtools/cli/legacy/IDP_merge_genepred.py
seqtools/cli/legacy/add_UCSC_URL_to_bed.py
seqtools/cli/legacy/annotate_psl_with_gpd.py
seqtools/cli/legacy/background.py
seqtools/cli/legacy/background_and_nascent_expression.py
seqtools/cli/legacy/bam_sort_list.py
seqtools/cli/legacy/bam_to_bed_depth_fast.py
seqtools/cli/legacy/bam_to_bed_exons.py
seqtools/cli/legacy/bam_to_best_bam.py
seqtools/cli/legacy/bam_to_downsampled_bam.py
seqtools/cli/legacy/bam_to_genepred.py
seqtools/cli/legacy/bam_to_longest_pacbio_molecule_bam.py
seqtools/cli/legacy/bam_to_ont_best_molecule_bam.py
seqtools/cli/legacy/bam_to_read_count.py
seqtools/cli/legacy/bam_to_vcf.py
seqtools/cli/legacy/bed_depth_to_bias_table.py
seqtools/cli/legacy/bed_depth_to_stratified_percentage_bed.py
seqtools/cli/legacy/bed_tools.py
seqtools/cli/legacy/bestannotation_into_rarefraction.py
seqtools/cli/legacy/bio_to_lengths.py
seqtools/cli/legacy/bwa_sam_to_gpd.py
seqtools/cli/legacy/cat_numerical.py
seqtools/cli/legacy/change_UCSC_bed_color.py
seqtools/cli/legacy/combine_bam.py
seqtools/cli/legacy/combine_splicemap_junction_color_bed.py
seqtools/cli/legacy/consecutive_junction_true_negative_detector.py
seqtools/cli/legacy/convert_BWA-mem_to_psl.py
seqtools/cli/legacy/defragment_PSL_alignments.py
seqtools/cli/legacy/du_threaded.py
seqtools/cli/legacy/explode_bam.py
seqtools/cli/legacy/explode_fastq.py
seqtools/cli/legacy/extract_ont_fastq.py
seqtools/cli/legacy/fasta_to_average_read_size.py
seqtools/cli/legacy/fastq_bgzf_index.py
seqtools/cli/legacy/fastq_quality_profiler.py
seqtools/cli/legacy/fastq_to_unmapped_sam.py
seqtools/cli/legacy/filter_psl.py
seqtools/cli/legacy/filter_sam_by_name_list.py
seqtools/cli/legacy/filter_sam_junctions.py
