Metadata-Version: 1.1
Name: seq-tools
Version: 1.0.10
Summary: Python tools for working with biological sequence data
Home-page: https://github.com/jason-weirather/py-seq-tools
Author: Jason L Weirather
Author-email: jason.weirather@gmail.com
License: Apache License, Version 2.0
Keywords: bioinformatics,sequence,alignment
Platform: UNKNOWN
Classifier: Development Status :: 3 - Alpha
Classifier: Intended Audience :: Science/Research
Classifier: Topic :: Scientific/Engineering :: Bio-Informatics
Classifier: License :: OSI Approved :: Apache Software License
